AUTHORS
LICENSE
MANIFEST.in
README.rst
setup.py
twisted/plugins/sockjs_endpoints.py
txsockjs/__init__.py
txsockjs/factory.py
txsockjs/multiplex.py
txsockjs/oldwebsockets.py
txsockjs/utils.py
txsockjs/websockets.py
txsockjs.egg-info/PKG-INFO
txsockjs.egg-info/SOURCES.txt
txsockjs.egg-info/dependency_links.txt
txsockjs.egg-info/requires.txt
txsockjs.egg-info/top_level.txt
txsockjs/protocols/__init__.py
txsockjs/protocols/base.py
txsockjs/protocols/eventsource.py
txsockjs/protocols/htmlfile.py
txsockjs/protocols/jsonp.py
txsockjs/protocols/static.py
txsockjs/protocols/websocket.py
txsockjs/protocols/xhr.py