Metadata-Version: 1.1
Name: txsockjs
Version: 1.2.0
Summary: Twisted SockJS wrapper
Home-page: http://github.com/Fugiman/sockjs-twisted
Author: Christopher Gamble
Author-email: chris@chrisgamble.net
License: BSD License
Platform: OS Independent
Classifier: Development Status :: 5 - Production/Stable
Classifier: Framework :: Twisted
Classifier: Intended Audience :: Developers
Classifier: License :: OSI Approved :: BSD License
Classifier: Operating System :: OS Independent
Classifier: Programming Language :: Python
Classifier: Topic :: Internet
